README.md
setup.py
dakiya/__init__.py
dakiya.egg-info/PKG-INFO
dakiya.egg-info/SOURCES.txt
dakiya.egg-info/dependency_links.txt
dakiya.egg-info/requires.txt
dakiya.egg-info/top_level.txt