Metadata-Version: 2.1
Name: dakiya
Version: 1.7
Summary: Relay Communcation via Nitro's Communication Hub
Author: Shamail Tayyab
Author-email: tayyab.shamail@gmail.com
Classifier: Programming Language :: Python :: 3
Classifier: License :: OSI Approved :: MIT License
Classifier: Operating System :: OS Independent
Requires-Dist: requests
